synthetic/__init__.py
synthetic/accessor_delegate.py
synthetic/decorators.py
synthetic/exceptions.py
synthetic/i_member_delegate.py
synthetic/i_naming_convention.py
synthetic/naming_convention_camel_case.py
synthetic/naming_convention_underscore.py
synthetic/property_delegate.py
synthetic/synthetic_class_controller.py
synthetic/synthetic_comparison_factory.py
synthetic/synthetic_constructor_factory.py
synthetic/synthetic_decorator_factory.py
synthetic/synthetic_member.py
synthetic/synthetic_meta_data.py
pysynthetic-0.5.3.dist-info/LICENSE.txt
pysynthetic-0.5.3.dist-info/METADATA
pysynthetic-0.5.3.dist-info/WHEEL
pysynthetic-0.5.3.dist-info/top_level.txt
pysynthetic-0.5.3.dist-info/RECORD
