Metadata-Version: 2.1
Name: pysynthetic
Version: 0.5.3
Summary: Easy Python class writing and type checking
Home-page: https://github.com/yjaaidi/pysynthetic
Download-URL: https://pypi.python.org/pypi/pysynthetic/
Author: Younes JAAIDI
Author-email: yjaaidi@gmail.com
Maintainer: Younes JAAIDI
Maintainer-email: yjaaidi@gmail.com
License: MIT
Platform: any
Classifier: Development Status :: 5 - Production/Stable
Classifier: License :: OSI Approved :: MIT License
Classifier: Programming Language :: Python :: 2
Classifier: Programming Language :: Python :: 3
Classifier: Topic :: Software Development
Classifier: Topic :: Software Development :: Code Generators
Classifier: Topic :: Utilities
Requires-Python: >=2.7
License-File: LICENSE.txt
Requires-Dist: pycontracts (>=1.7.8)
